valve_gfx_ci/valvetraces/__init__.py
valve_gfx_ci.valvetraces-0.0.18.dist-info/LICENSE
valve_gfx_ci.valvetraces-0.0.18.dist-info/METADATA
valve_gfx_ci.valvetraces-0.0.18.dist-info/WHEEL
valve_gfx_ci.valvetraces-0.0.18.dist-info/entry_points.txt
valve_gfx_ci.valvetraces-0.0.18.dist-info/top_level.txt
valve_gfx_ci.valvetraces-0.0.18.dist-info/RECORD
