Metadata-Version: 2.1
Name: valve-gfx-ci.valvetraces
Version: 0.0.18
Summary: Interact with Valve's GFX trace system
Home-page: https://gitlab.freedesktop.org/mupuf/valve-infra/-/tree/master/valvetraces
Author: Martin Roukala
Author-email: martin.roukala@mupuf.org
Project-URL: Bug Tracker, https://gitlab.freedesktop.org/mupuf/valve-infra/issues
Classifier: Programming Language :: Python :: 3
Classifier: License :: OSI Approved :: MIT License
Classifier: Operating System :: OS Independent
Requires-Python: >=3.6
License-File: LICENSE
Requires-Dist: requests (<3,>=2)
Requires-Dist: humanize (>=3.3.0)
Requires-Dist: Pillow (>=5.4.0)
Requires-Dist: pygit2 (>=1.4.0)
Requires-Dist: minio (>=7.1.0)
Requires-Dist: valve-gfx-ci.executor.client
Requires-Dist: backports.cached-property ; python_version < "3.8"
